{"atualizar": [0, 10], "drivers": [0], "windows": [0, 3, 5, 7], "acesse": [0], "update": [0], "busca": [0], "10": [0], "digite": [0, 7], "confira": [0], "atualiza\u00e7\u00f5es": [0], "instale": [0, 6, 10], "novos": [0], "instalar": [0, 9], "existirem": [0], "reinicie": [0, 3, 6], "siga": [1, 5, 7], "dicas": [1, 3], "diminuir": [1], "barulho": [1], "cooler": [1, 8], "computador": [1, 3, 6, 8, 9, 11], "limpe": [1, 3, 10], "aperte": [1, 9], "parafusos": [1], "altere": [1, 6], "plano": [1], "energia": [1, 2, 8, 9], "pare": [1], "processos": [1], "consumo": [1], "recursos": [1], "coloque": [1, 3], "pc": [1, 2, 3, 4, 8], "fresco": [1], "obstru\u00e7\u00f5es": [1], "desligando": [2], "sozinho": [2], "significar": [2], "diferentes": [2], "tipos": [2], "problema": [2, 3, 4, 8], "descuidos": [2], "como": [2, 5, 8, 9], "fonte": [2, 8], "voltagem": [2], "errada": [2], "carregador": [2], "laptop": [2], "especifica\u00e7\u00f5es": [2], "abaixo": [2], "m\u00ednimo": [2], "exigido": [2], "situa\u00e7\u00f5es": [2], "graves": [2], "envolvendo": [2], "instala\u00e7\u00e3o": [2, 9], "hardware": [2], "lento": [3], "comum": [3, 10], "otimizar": [3], "desempenho": [3, 4, 9], "ocasionalmente": [3], "desative": [3], "programas": [3], "inicializam": [3], "fa\u00e7a": [3, 8, 10], "varredura": [3], "antiv\u00edrus": [3], "use": [3, 10], "software": [3, 6, 9], "limpeza": [3], "arquivos": [3, 5, 6, 7], "frequentemente": [3], "desfragmente": [3], "disco": [3, 9], "troca": [3], "hd": [3], "ssd": [3, 4], "mem\u00f3ria": [3, 4], "ram": [3, 4], "games": [4], "online": [4], "alta": [4], "performance": [4], "tornaram": [4], "mercado": [4], "internacional": [4], "conseguir": [4], "preciso": [4], "contar": [4], "componentes": [4, 8], "modo": [4, 6], "citados": [4], "relevantes": [4], "comprar": [4], "gamerusar": [4], "armazenamento": [4, 7, 9], "12": [4], "gb": [4], "processador": [4, 8], "core": [4], "i5": [4], "superior": [4], "placa": [4, 8], "v\u00eddeo": [4], "essencial": [4], "jogar": [4], "principais": [4, 10], "jogos": [4], "nenhum": [4], "formata\u00e7\u00e3o": [5], "simples": [5, 6, 10], "recomendado": [5], "realize": [5], "backup": [5, 7, 9], "passos": [5, 7], "formatar": [5, 9], "pcabra": [5], "menu": [5, 9], "clique": [5, 9], "\u00edcone": [5], "\u201cconfigura\u00e7\u00f5es\u201dagora": [5], "basta": [5, 9, 10], "selecionar": [5], "chamado": [5], "\u201catualiza\u00e7\u00e3o": [5], "seguran\u00e7a\u201dna": [5], "barra": [5, 7], "lateral": [5], "esquerda": [5, 9], "tela": [5, 9], "\u201crecupera\u00e7\u00e3o\u201d": [5], "v\u00e1": [5], "op\u00e7\u00e3o": [5, 9], "\u201crestaurar": [5], "pc\u201dfeito": [5], "acesso": [5], "restaura\u00e7\u00e3o": [5, 7], "inicie": [5], "processo": [5, 9], "clicando": [5], "\u201ccome\u00e7ar": [5], "agora\u201dchegou": [5], "seguir": [5, 10], "instru\u00e7\u00f5es": [5, 7], "solicitadoem": [5], "seguida": [5, 9], "aguarde": [5], "finalizar": [5, 9], "v\u00edrus": [6], "etapas": [6], "ajudar\u00e3o": [6], "livrar": [6], "baixe": [6], "verificador": [6], "desconectese": [6], "internet": [6, 9], "seguran\u00e7a": [6], "exclua": [6], "tempor\u00e1rios": [6], "execute": [6], "verifica\u00e7\u00e3o": [6], "coloqueo": [6], "quarentena": [6], "senhas": [6], "atualize": [6, 10], "navegador": [6], "operacional": [6], "restaurar": [7], "criado": [7], "hist\u00f3rico": [7], "conex\u00e3o": [7, 9], "dispositivo": [7], "externo": [7], "cont\u00e9m": [7], "caixa": [7], "pesquisa": [7], "tarefas": [7], "painel": [7], "controle": [7], "selecioneo": [7], "lista": [7, 9], "resultados": [7], "selecione": [7, 9], "7": [7, 9], "prov\u00e1vel": [8], "algum": [8], "pe\u00e7a": [8], "respons\u00e1vel": [8], "repassar": [8], "segura": [8], "n\u00e3o": [8, 9, 10, 11], "ligar": [8], "certifiquese": [8, 9, 11], "el\u00e9trica": [8], "casa": [8], "estabilizador": [8], "teste": [8], "funcionar": [8], "sabemos": [8], "qual": [8], "problemaassim": [8], "m\u00e3e": [8], "luz": [8, 11], "power": [8], "acende": [8], "acontece": [8], "verifique": [8, 10, 11], "cabos": [8], "conectados": [8], "corretamente": [8], "principalmente": [8], "alimenta\u00e7\u00e3o": [8], "olhe": [8], "calma": [8], "procure": [8], "capacitor": [8], "estourado": [8], "alguma": [8], "trilha": [8], "queimadaum": [8], "sinais": [8], "importantes": [8], "cpu": [8], "defeito": [8], "sinal": [8], "ok": [8], "ventoinha": [8], "girando": [8], "ind\u00edcio": [8], "usu\u00e1rios": [9], "apple": [9], "mac": [9], "reinstalar": [9], "macos": [9], "ajuda": [9], "m\u00eddia": [9], "f\u00edsica": [9], "cd": [9], "pendrive": [9], "macbook": [9], "imac": [9], "mini": [9], "pro": [9], "conectado": [9, 11], "rede": [9], "wifi": [9], "executar": [9], "comandos": [9], "corretos": [9], "recupera\u00e7\u00e3o": [9], "obter": [9], "c\u00f3pia": [9], "original": [9], "via": [9], "internetpasso": [9], "1": [9], "dados": [9], "removeu": [9], "credenciais": [9], "medo": [9], "desligue": [9], "bot\u00e3o": [9], "novamente": [9], "mantenha": [9], "pressionadas": [9], "teclas": [9], "command": [9], "": [9], "r": [9], "inicializa\u00e7\u00e3opasso": [9], "2": [9], "correr": [9], "pular": [9], "acessar": [9], "marque": [9], "\u201cutilit\u00e1rio": [9], "disco\u201d": [9], "\u201ccontinuar\u201dpasso": [9], "3": [9], "interno": [9], "\u201capagar\u201d": [9], "superiorpasso": [9], "4": [9], "formato": [9], "apfs": [9], "selecionado": [9], "\u201capagar\u201dpasso": [9], "5": [9], "feche": [9], "janela": [9], "utilit\u00e1rio": [9], "\u201creinstalar": [9], "macos\u201dpasso": [9], "6": [9], "vers\u00e3o": [9], "recente": [9], "dispon\u00edvel": [9], "abrir": [9], "redes": [9], "fio": [9], "dispon\u00edveis": [9], "conectese": [9], "ativa": [9], "download": [9], "zeropasso": [9], "8": [9], "aceite": [9], "termos": [9], "uso": [9], "avan\u00e7arpasso": [9], "9": [9], "\u201cinstalar\u201d": [9], "procedimento": [9], "totalmente": [9], "automatizado": [9], "leva": [9], "minutos": [9], "completar": [9], "depender": [9], "velocidade": [9], "\u2013": [9], "quanto": [9], "r\u00e1pida": [9], "poderoso": [9], "levar\u00e1": [9], "impressora": [10], "imprimindo": [10], "saiba": [10], "erro": [10], "resolvido": [10], "eliminar": [10], "documento": [10], "pendente": [10], "driver": [10], "pequenas": [10], "mudan\u00e7as": [10], "configura\u00e7\u00f5es": [10], "m\u00e1quina": [10], "imprima": [10], "novamenteveja": [10], "motivos": [10], "impress\u00e3o": [10], "respectivas": [10], "solu\u00e7\u00f5es1": [10], "fila": [10], "impress\u00e3o2": [10], "desconecte": [10], "reconecte": [10], "dispositivos3": [10], "cartuchos4": [10], "downgrade": [10], "firmware": [10], "modelos": [10], "hp5": [10], "resete": [10], "impressora6": [10], "solu\u00e7\u00e3o": [10], "problemas": [10], "windows7": [10], "driver8": [10], "assist\u00eancia": [10], "t\u00e9cnica": [10], "mouse": [11], "cabo": [11], "firmemente": [11], "computadorse": [11], "usb": [11], "conector": [11], "retangular": [11], "conect\u00e1lo": [11], "porta": [11], "diferente": [11], "ps2": [11], "redondo": [11], "pequeno": [11], "pinos": [11], "plugado": [11], "verde": [11], "inv\u00e9s": [11], "teclado": [11], "roxa": [11], "reiniciar": [11], "antesconecte": [11], "funcionase": [11], "\u00f3ptico": [11], "laser": [11], "deveria": [11], "brilhando": [11], "embaixo": [11], "ativado": [11], "defeituoso": [11]}